osmon/__init__.py
osmon/__main__.py
osmon-0.1.5.dist-info/LICENSE
osmon-0.1.5.dist-info/METADATA
osmon-0.1.5.dist-info/WHEEL
osmon-0.1.5.dist-info/entry_points.txt
osmon-0.1.5.dist-info/top_level.txt
osmon-0.1.5.dist-info/RECORD
