Metadata-Version: 2.1
Name: osmon
Version: 0.1.5
Summary: Simple cli system monitor made for fun.
Home-page: https://github.com/a1eaiactaest/osmon
Author: Piotrek Rybiec
License: MIT
Platform: UNKNOWN
Classifier: Programming Language :: Python :: 3
Classifier: License :: OSI Approved :: MIT License
Requires-Dist: argparse
Requires-Dist: gpuinfo
Requires-Dist: psutil
Requires-Dist: speedtest-cli
